build/lib/build/lib/build/lib/build/lib/build/lib/build/lib/build/lib/societeinfo/__init__.py
build/lib/build/lib/build/lib/build/lib/build/lib/build/lib/build/lib/societeinfo/exceptions.py
build/lib/build/lib/build/lib/build/lib/build/lib/build/lib/build/lib/tests/test_autocomplete_companies.py
build/lib/build/lib/build/lib/build/lib/build/lib/build/lib/build/lib/tests/test_get_company_by_id.py
build/lib/build/lib/build/lib/build/lib/build/lib/build/lib/build/lib/tests/test_get_credit_details.py
build/lib/build/lib/build/lib/build/lib/build/lib/build/lib/build/lib/tests/test_societeinfoclient_class.py
build/lib/build/lib/build/lib/build/lib/build/lib/build/lib/societeinfo/__init__.py
build/lib/build/lib/build/lib/build/lib/build/lib/build/lib/societeinfo/exceptions.py
build/lib/build/lib/build/lib/build/lib/build/lib/build/lib/tests/test_autocomplete_companies.py
build/lib/build/lib/build/lib/build/lib/build/lib/build/lib/tests/test_get_company_by_id.py
build/lib/build/lib/build/lib/build/lib/build/lib/build/lib/tests/test_get_credit_details.py
build/lib/build/lib/build/lib/build/lib/build/lib/build/lib/tests/test_societeinfoclient_class.py
build/lib/build/lib/build/lib/build/lib/build/lib/societeinfo/__init__.py
build/lib/build/lib/build/lib/build/lib/build/lib/societeinfo/exceptions.py
build/lib/build/lib/build/lib/build/lib/build/lib/tests/test_autocomplete_companies.py
build/lib/build/lib/build/lib/build/lib/build/lib/tests/test_get_company_by_id.py
build/lib/build/lib/build/lib/build/lib/build/lib/tests/test_get_credit_details.py
build/lib/build/lib/build/lib/build/lib/build/lib/tests/test_societeinfoclient_class.py
build/lib/build/lib/build/lib/build/lib/societeinfo/__init__.py
build/lib/build/lib/build/lib/build/lib/societeinfo/exceptions.py
build/lib/build/lib/build/lib/build/lib/tests/test_autocomplete_companies.py
build/lib/build/lib/build/lib/build/lib/tests/test_get_company_by_id.py
societeinfo-1.1.0.dist-info/LICENSE.md
societeinfo-1.1.0.dist-info/METADATA
societeinfo-1.1.0.dist-info/WHEEL
societeinfo-1.1.0.dist-info/top_level.txt
societeinfo-1.1.0.dist-info/RECORD
